django_templater/__dt_main__.py
django_templater/__dtt_main__.py
django_templater/__init__.py
django_templater/shared.py
django_templater-0.2.0.dist-info/LICENSE
django_templater-0.2.0.dist-info/METADATA
django_templater-0.2.0.dist-info/WHEEL
django_templater-0.2.0.dist-info/entry_points.txt
django_templater-0.2.0.dist-info/RECORD
