Metadata-Version: 2.1
Name: django-templater
Version: 0.2.0
Summary: 
Author: cr0hn
Author-email: cr0hn@cr0hn.com
Requires-Python: >=3.11,<4.0
Classifier: Programming Language :: Python :: 3
Classifier: Programming Language :: Python :: 3.11
Classifier: Programming Language :: Python :: 3.12
Requires-Dist: lxml (>=4.9.3,<5.0.0)
Requires-Dist: requests (>=2.31.0,<3.0.0)
